precogs/__init__.py
precogs/client.py
precogs/exceptions.py
precogs/http.py
precogs/resources.py
precogs_sdk-0.1.2.dist-info/METADATA
precogs_sdk-0.1.2.dist-info/WHEEL
precogs_sdk-0.1.2.dist-info/licenses/LICENSE
precogs_sdk-0.1.2.dist-info/RECORD
