Metadata-Version: 2.4
Name: precogs-sdk
Version: 0.1.2
Summary: Official Python SDK for Precogs AI - Security-first code analysis
Project-URL: Homepage, https://precogs.ai
Project-URL: Documentation, https://docs.precogs.ai
Project-URL: Repository, https://github.com/precogsai/precogs-sdk
Project-URL: Issues, https://github.com/precogsai/precogs-sdk/issues
Author-email: Precogs AI <support@precogs.ai>
License-Expression: MIT
License-File: LICENSE
Keywords: code-analysis,devsecops,sast,security,vulnerability
Classifier: Development Status :: 4 - Beta
Classifier: Intended Audience :: Developers
Classifier: License :: OSI Approved :: MIT License
Classifier: Programming Language :: Python :: 3
Classifier: Programming Language :: Python :: 3.8
Classifier: Programming Language :: Python :: 3.9
Classifier: Programming Language :: Python :: 3.10
Classifier: Programming Language :: Python :: 3.11
Classifier: Programming Language :: Python :: 3.12
Classifier: Topic :: Security
Classifier: Topic :: Software Development :: Quality Assurance
Requires-Python: >=3.8
Requires-Dist: httpx>=0.24.0
Requires-Dist: pydantic>=2.0.0
Provides-Extra: dev
Requires-Dist: pytest-asyncio>=0.21.0; extra == 'dev'
Requires-Dist: pytest>=7.0.0; extra == 'dev'
Requires-Dist: ruff>=0.1.0; extra == 'dev'
